chuangsiai_sdk/__init__.py
chuangsiai_sdk/auth.py
chuangsiai_sdk/client.py
chuangsiai_sdk/config.ini
chuangsiai_sdk/exceptions.py
chuangsiai_sdk/models.py
chuangsiai_sdk/utils.py
chuangsiai_sdk-1.1.2.dist-info/licenses/LICENSE
chuangsiai_sdk-1.1.2.dist-info/METADATA
chuangsiai_sdk-1.1.2.dist-info/WHEEL
chuangsiai_sdk-1.1.2.dist-info/top_level.txt
chuangsiai_sdk-1.1.2.dist-info/RECORD
