Metadata-Version: 2.4
Name: chuangsiai-sdk
Version: 1.1.2
Summary: 创思大模型安全工具是一款面向大语言模型的内容安全防护系统，旨在识别和拦截 LLM 输入与输出中的潜在安全风险，包括涉政敏感、色情、违法违规行为、负面价值导向、辱骂言论及隐私泄露等内容。针对存在风险的输入，该工具还支持安全可信代答，助力用户实现大模型系统的安全合规。
Author-email: Chuangsiai <service@chuangsiai.com>
License: MIT
Project-URL: Homepage, https://github.com/chuangsiaihub/chuangsiai-sdk
Project-URL: Source, https://github.com/chuangsiaihub/chuangsiai-sdk
Classifier: Development Status :: 5 - Production/Stable
Classifier: Intended Audience :: Developers
Classifier: Operating System :: OS Independent
Classifier: Programming Language :: Python
Classifier: Programming Language :: Python :: 3
Classifier: Programming Language :: Python :: 3.8
Classifier: Programming Language :: Python :: 3.9
Classifier: Programming Language :: Python :: 3.10
Classifier: Programming Language :: Python :: 3.11
Classifier: Topic :: Software Development :: Libraries
Requires-Python: >=3.8
License-File: LICENSE
Requires-Dist: requests>=2.25.0
Requires-Dist: pydantic>=2.0.0
Dynamic: license-file
